{
    "op1": "Pokémon Theme",
    "op2": "Pokémon World",
    "op3": "Pokémon Johto",
    "op4": "Born to Be a Winner",
    "op5": "Believe in Me",
    "op6": "I Wanna Be a Hero",
    "op7": "This Dream",
    "op8": "Unbeatable",
    "op9": "Battle Frontier",
    "op10": "Diamond and Pearl",
    "op11": "We Will Be Heroes",
    "op12": ["Battle Cry", "Stand Up!","Battle Cry Stand Up!", "Battle Cry Stand Up"],
    "op13": "We Will Carry On!",
    "op14": "Black and White",
    "op15": "Rival Destinies",
    "op16": "It's Always You and Me",
    "op17": "Pokémon Theme (Version XY)",
    "op18": "Be a Hero",
    "op19": "Stand Tall",
    "op20": "Under The Alolan Sun",
    "op21": "Under The Alolan Moon",
    "op22": "The Challenge of Life",
    "op23": "The Journey Starts Today",
    "op24": "Journey to Your Heart",
    "op25": "With You",
    "op26": "Gotta Catch Em All",
    "op27": "Becoming Me"
  }
  
